aws_comprehend/__init__.py
aws_comprehend/_version.py
aws_comprehend/api.py
aws_comprehend/compat.py
aws_comprehend/comprehend_csv.py
aws_comprehend/exc.py
aws_comprehend/paths.py
aws_comprehend/better_boto/__init__.py
aws_comprehend/better_boto/api.py
aws_comprehend/better_boto/document_classifier.py
aws_comprehend/better_boto/endpoint.py
aws_comprehend/docs/__init__.py
aws_comprehend/tests/__init__.py
aws_comprehend/tests/boto_ses.py
aws_comprehend/tests/helper.py
aws_comprehend/tests/paths.py
aws_comprehend/vendor/__init__.py
aws_comprehend/vendor/pytest_cov_helper.py
aws_comprehend/vendor/waiter.py
aws_comprehend-0.1.2.dist-info/AUTHORS.rst
aws_comprehend-0.1.2.dist-info/LICENSE.txt
aws_comprehend-0.1.2.dist-info/METADATA
aws_comprehend-0.1.2.dist-info/WHEEL
aws_comprehend-0.1.2.dist-info/top_level.txt
aws_comprehend-0.1.2.dist-info/RECORD
